smolrouter/__init__.py
smolrouter/access_control.py
smolrouter/app.py
smolrouter/auth.py
smolrouter/caching.py
smolrouter/cli.py
smolrouter/container.py
smolrouter/database.py
smolrouter/interfaces.py
smolrouter/mediator.py
smolrouter/providers.py
smolrouter/routing.py
smolrouter/security.py
smolrouter/storage.py
smolrouter/strategies.py
smolrouter-1.0.0.dist-info/licenses/LICENSE
smolrouter-1.0.0.dist-info/METADATA
smolrouter-1.0.0.dist-info/WHEEL
smolrouter-1.0.0.dist-info/entry_points.txt
smolrouter-1.0.0.dist-info/top_level.txt
smolrouter-1.0.0.dist-info/RECORD
