Metadata-Version: 2.4
Name: SmolRouter
Version: 1.0.0
Summary: A smart, lightweight proxy for routing AI model requests with performance analytics.
Author-email: Mitchell Currie <mitchell.currie@gmail.com>
Project-URL: Homepage, https://github.com/mitchins/smolrouter
Project-URL: Bug Tracker, https://github.com/mitchins/smolrouter/issues
Classifier: Programming Language :: Python :: 3
Classifier: License :: OSI Approved :: MIT License
Classifier: Operating System :: OS Independent
Requires-Python: >=3.7
License-File: LICENSE
Requires-Dist: fastapi
Requires-Dist: httpx
Requires-Dist: uvicorn[standard]
Requires-Dist: peewee
Requires-Dist: jinja2
Requires-Dist: pyyaml
Requires-Dist: pyjwt
Requires-Dist: slowapi
Provides-Extra: dev
Requires-Dist: pytest; extra == "dev"
Requires-Dist: pytest-asyncio; extra == "dev"
Requires-Dist: pytest-cov; extra == "dev"
Requires-Dist: pytest-mock; extra == "dev"
Requires-Dist: respx; extra == "dev"
Requires-Dist: flake8; extra == "dev"
Requires-Dist: flake8-bugbear; extra == "dev"
Requires-Dist: flake8-comprehensions; extra == "dev"
Requires-Dist: flake8-simplify; extra == "dev"
Requires-Dist: vulture; extra == "dev"
Requires-Dist: pre-commit; extra == "dev"
Requires-Dist: ruff; extra == "dev"
Dynamic: license-file
